LICENSE
README.md
pyproject.toml
setup.cfg
mmif_docloc_baapb/__init__.py
mmif_docloc_baapb.egg-info/PKG-INFO
mmif_docloc_baapb.egg-info/SOURCES.txt
mmif_docloc_baapb.egg-info/dependency_links.txt
mmif_docloc_baapb.egg-info/top_level.txt
tests/test_baapb_handler.py