Metadata-Version: 2.4
Name: mmif_docloc_baapb
Version: 250809
Summary: a plugin to mmif-python to handle `baapb` location scheme
Author: "Brandeis Lab for Linguistics and Computation"
Author-email: "admin@clams.ai"
License: Apache-2.0
License-File: LICENSE
Dynamic: license-file
